ALU.v

module ALU(
    input logic [31:0] a, b,
    input logic [3:0] ctrl,
    output logic [31:0] out,
    output logic [1:0] comp,
    //output logic [63:0] total, stotal,
    input logic clk
);
    //signals and module for division
    logic S;
    logic [31:0] divq, divr;
    //div divcirc(.a(a), .b(b), .signdiv(S), .q(divq), .r(divr));

    //hi, lo and internal values for multiplication
    logic [31:0] hi, lo, shi, slo;
    logic [4:0] constto;
    logic [31:0] amag, bmag; //magnitude of a and b

    //used a constant decimal 31 as Icarus doesn't support constant indexing
    initial begin
        constto <= 5'b11111;
    end

    always_comb begin
        //always computing both MULT and MULTU instead of using an if reduces the critical path at the expense of circuit compactness,
        //though it is likely that the time gain is far less significant than the area increase.

        //unsigned product, total is just for testing
        {hi, lo} = a*b;
        //total = a*b;

        //signed product, stotal is just for testing
        amag = a[constto] ? (~a + 1) : a;
        bmag = b[constto] ? (~b + 1) : b;
        {shi, slo} = (a[constto] ^ b[constto]) ? ( ~(amag * bmag) + 1 ) : (amag*bmag);
        //stotal = (a[constto] ^ b[constto]) ? ( ~(amag * bmag) + 1 ) : (amag*bmag);
        
    end

    always_comb begin
       
			if ($signed(a) == $signed(b)) begin
				comp = 2'b00;
			end else if 
			($signed(a) < $signed(b)) begin
				comp = 2'b01;
			end else if	
			($signed(a) > $signed(b)) begin
				comp = 2'b10;
			end

        case(ctrl)
            4'b0000: out = a + b;   //ADD
            4'b0001: out = a - b;   //SUB
            4'b0010: out = a & b;   //AND bitwise
            4'b0011: out = a | b;   //OR bitwise
            4'b0100: out = a ^ b;   //XOR bitwise
            4'b0101: out = a<<b;  //SLL 
            4'b0110: out = a>>b;  //SRL
            4'b0111: out = a>>>b; //SRA 

            4'b1001: out = shi;         //MULT TOP
            4'b1000: out = slo; //MULT BOT
            4'b1011: begin
                out = hi;       //MULTU TOP
            end
            4'b1010: begin
                out = lo; //MULTU BOT
            end         
            /*4'b1100: begin //DIV
                S = 1;
                out = divq;
            end     
            4'b1101: begin //MOD
                S = 1;
                out = divr;
            end     
            4'b1110: begin //DIVU
                S = 0;
                out = divq;
            end      
            4'b1111: begin //MODU
                S = 0;
                out = divr;
            end*/
            //placeholder for DIV and MOD operations
            4'b1100: out = 32'h00000000; 
            4'b1101: out = 32'h00000000; 
            4'b1110: out = 32'h00000000; 
            4'b1111: out = 32'h00000000;       
        endcase
    end
endmodule

ALU_mult_tb.v
module ALU_mult_tb;
    logic clk;
    logic [31:0] a, b;
    logic [3:0] ctrl;
    logic [31:0] result;
    logic [1:0] comp;

    ALU ALU_DUT(
        .a(a), .b(b),
        .ctrl(ctrl),
        .out(result)
    );

    initial begin
        clk = 0;
        repeat(0) begin
            #1
            clk = !clk;
            #1
            clk = !clk;
        end
    end

    initial begin
        a = 5;
        b = 4;
        ctrl = 4'b1010;
        @(posedge clk);
        ctrl = 4'b1011;
        @(posedge clk);
        a = 4;
        b = 3;
        ctrl = 4'b1010;
        @(posedge clk);
        ctrl = 4'b1011;
        @(posedge clk);
        a = 2111222333;
        b = 2;
        ctrl = 4'b1010;
        @(posedge clk);
        ctrl = 4'b1011;
        @(posedge clk);
        a = 2111222333;
        b = 2111222333;
        ctrl = 4'b1010;
        @(posedge clk);
        ctrl = 4'b1011;
        @(posedge clk);
    end
endmodule

ALU_mult_waves.vcd
$date
	Mon Dec 14 20:42:38 2020
$end
$version
	Icarus Verilog
$end
$timescale
	1s
$end
$scope module ALU_mult_tb $end
$scope module ALU_DUT $end
$var wire 32 ! a [31:0] $end
$var wire 32 " b [31:0] $end
$var wire 1 # clk $end
$var wire 4 $ ctrl [3:0] $end
$var reg 32 % amag [31:0] $end
$var reg 32 & bmag [31:0] $end
$var reg 2 ' comp [1:0] $end
$var reg 5 ( constto [4:0] $end
$var reg 32 ) hi [31:0] $end
$var reg 32 * lo [31:0] $end
$var reg 32 + out [31:0] $end
$var reg 32 , shi [31:0] $end
$var reg 32 - slo [31:0] $end
$upscope $end
$upscope $end
$enddefinitions $end
#0
$dumpvars
b11111111111111110010000001011000 -
b11111111111111111111111111111111 ,
b11111111111111110010000001011000 +
b11111111111111110010000001011000 *
b11010010011 )
b11111 (
b10 '
b100010 &
b11010010100 %
b1010 $
0#
b11111111111111111111111111011110 "
b11010010100 !
$end
#1
b11010010011 +
b1011 $
1#
#2
0#
#3
b1100 +
b0 ,
b1100 -
b11 &
b100 %
b0 )
b1100 *
b1010 $
b11 "
b100 !
1#
#4
0#
#5
b0 +
b1011 $
1#
#6
0#
#7
b11111011101011010110010001111010 +
b11111011101011010110010001111010 -
b10 &
b1111101110101101011001000111101 %
b11111011101011010110010001111010 *
b1010 $
b10 "
b1111101110101101011001000111101 !
1#
#8
0#
#9
b0 +
b1011 $
1#
#10
0#
#11
b1100000101001110001010001001 +
b0 '
b111101110110110101111000011110 ,
b1100000101001110001010001001 -
b1111101110101101011001000111101 &
b111101110110110101111000011110 )
b1100000101001110001010001001 *
b1010 $
b1111101110101101011001000111101 "
1#
#12
0#
#13
b111101110110110101111000011110 +
b1011 $
1#
#14
0#
#15
b11111111111111110010000001011000 +
b10 '
b11111111111111111111111111111111 ,
b11111111111111110010000001011000 -
b100010 &
b11010010100 %
b11010010011 )
b11111111111111110010000001011000 *
b1000 $
b11111111111111111111111111011110 "
b11010010100 !
1#
#16
0#
#17
b11111111111111111111111111111111 +
b1001 $
1#
#18
0#
#19
b1100 +
b1 '
b0 ,
b1100 -
b11 &
b100 %
b11111111111111111111111111111001 )
b1100 *
b1000 $
b11111111111111111111111111111101 "
b11111111111111111111111111111100 !
1#
#20
0#
#21
b0 +
b1001 $
1#
#22
0#
#23
b11111111111111111110111101111110 +
b11111111111111111111111111111111 ,
b11111111111111111110111101111110 -
b10 &
b100001000001 %
b1 )
b11111111111111111110111101111110 *
b1000 $
b10 "
b11111111111111111111011110111111 !
1#
#24
0#
#25
b11111111111111111111111111111111 +
b1001 $
1#
#26
0#
#27
b10000010001010010100110111000011 +
b10000010001010010100110111000011 -
b1111101110101101011001000111101 &
b1 %
b1111101110101101011001000111100 )
b10000010001010010100110111000011 *
b1000 $
b1111101110101101011001000111101 "
b11111111111111111111111111111111 !
1#
#28
0#
#29
b11111111111111111111111111111111 +
b1001 $
1#
