divu.v
module divu(
    //division algorithm requires a that has been shifted left such that newa<b<2*newa
    input logic [31:0] divua, divub, realb,
	input logic clk, divurst,
    output logic [31:0] divuq, divur
	//output logic divudone
);
    logic [31:0] rega, regb, quotient;
	//logic finished;

	 //takes many cycles, requires rst to be high during clk posedge
	 
	 always_comb begin
		divuq = quotient;
		divur = rega;
		//divudone = finished;
	 end
	 
	 always_ff@ ( posedge clk, negedge clk ) begin
			if(divurst == 1) begin
				quotient <= 32'h00000000;
				rega <= divua;
				regb <= divub;
				//finished <= 0;
			end else begin
			
				if(regb < realb) begin
					//make this happen a cycle earlier
					//finished <= 1;
				end else begin
					if (rega >= regb) begin
						rega <= (rega - regb);
						quotient <= ((quotient << 1) + 1); 

					end else begin
						rega <= rega;
						quotient <= (quotient << 1);
						
					end
					regb <= (regb >> 1);
				end
						
			end
						
	 end

endmodule

align.v
//the module prepares the division a/b by shifting b left as much as possible while still having b<a
module align (
	input logic clk, alrst,
	input logic [31:0] ala, alb,
	output logic [31:0] shiftb 
);
	logic [31:0] shifted;
	logic [15:0] ahi, alo;
	//the bs have an extra bit to avoid overflow when shifting  
	logic [16:0] bhi, blo;
	logic [4:0] i, blo_cnt;
	logic end_lo, ahizero;
	
	//constantly update output (shifted b value)
	always_comb begin
		shiftb = shifted;
	end

	always_ff @(posedge clk, negedge clk) begin

		if(alrst == 1) begin
            //to reduce CPI, a and b are divided into two halves
			ahi <= ala[31:16];
			alo <= ala[15:0];
			bhi <= alb[31:16];
			blo <= alb[15:0];
			i <= 5'b00000;
			blo_cnt <= 5'h00;
			shifted <= 32'h00000000; 
			end_lo <= 0;
			ahizero <= ( ala[31:16] == 16'h0000 );
		end else begin
				
            //shift both b halves and compare to a half-words, 
			//thus determine amount by which to shift whole b.
			if (bhi > ahi) begin
				shifted <= (alb<<(i-1));
			end else begin
				if(i == 5'b10000) begin
					//if bhi has been shifted without finding a value > ahi, look to results from blo
					//this may be less efficient than a method that checks if bhi is empty
					if( ahizero == 1 ) begin
						shifted <= (alb<<(blo_cnt-1));
					end else begin
						shifted <= {alb<<(blo_cnt-1), {16'h0000} };
					end					
				end else begin
					i <= (i + 1);
					bhi <= (bhi << 1);
				end
			end
	
	
			if(end_lo == 0) begin
				//checks blo against ahi and alo for both cases: ahi is and isn't zero
				if( ( (blo > alo) & (ahizero == 1) ) | ( (blo > ahi) & (ahizero == 0) ) ) begin
					end_lo <= 1;
				end else begin
					blo <= (blo << 1);
					blo_cnt <= (blo_cnt + 1);
				end
			end
						
		end
		
	end
	
endmodule

div.v
//DIV, currently broken

module div(
    input logic [31:0] a, b,
    input logic signdiv, clk, divrst,
    output logic [31:0] q, r
	//output logic done
);

	logic nxt;
	//internal operand and result values, as division is unsigned and begins with the divisor shifted to the MSB of quotient (unclear explanation)
	logic [31:0] ua, ub, shiftedb, uq, ur;

	logic [4:0] constind, aligncnt;

	align aligner (
		.clk(clk), .alrst(divrst), 
		.ala(ua), .alb(ub), .shiftb(shiftedb)
		//.aldone(aligndone)
	);

	divu divider (
		.clk(clk), .divurst(nxt),
		.divua(ua), .divub(shiftedb), .realb(ub),
		.divuq(uq), .divur(ur)
		//.divudone(done)
	);

	initial begin
		constind <= 5'b11111;
		//nxt <= 0;
		//buff <= 0;
		aligncnt <= 0;
		nxt <= 0;
	end

	
	always_ff @(posedge clk) begin
		
		if(aligncnt < 5'h12 ) begin
			aligncnt <= (aligncnt + 1);
		end

		if(aligncnt == 5'h11) begin
			nxt <= 1;
		end else begin
			nxt <= 0;
		end
		
	end

	//properly assign operands, quotient and remainder for signed/unsigned division and the signs of each operand 
	always_comb begin
		if(signdiv == 1) begin
			if( a[constind] == 1 ) begin
				ua = ~(a - 1);
				r = ~ur + 1;
			end else begin
				ua = a;
				r = ur;
			end

			if( b[constind] == 1 ) begin
				ub = ~(b - 1);
			end else begin
				ub = b;
			end

			if( a[constind] ^ b[constind] ) begin
				q = ~uq + 1;
			end else begin
				q = uq;
			end

		end else begin
			ua = a;
			ub = b;
			q = uq;
			r = ur;
		end
	end	
	
endmodule

div_tb.v
module div_tb;

    logic clk, rst, signdiv, done;
    logic [31:0] dividend, divisor, quotient, remainder;

    div division(
        .a(dividend), .b(divisor),
        .clk(clk), .divrst(rst), .signdiv(signdiv),
        .q(quotient), .r(remainder)
        //.done(done)
    );

    initial begin
        clk = 0;
        repeat (70) begin
            #10
            clk = !clk;
            #10
            clk = !clk;
        end
    end

    initial begin
        rst <= 0;
        dividend <= 32'hF0000000;
        divisor <= 32'h00000001;
        signdiv <= 0;
        @(posedge clk);
        rst <= 1;
        @(posedge clk);
        rst <= 0;

        $dumpfile("div_waves.vcd");
        $dumpvars(0,division);
    end

endmodule

div_waves.vcd
$date
	Fri Dec 11 18:21:08 2020
$end
$version
	Icarus Verilog
$end
$timescale
	1s
$end
$scope module div_tb $end
$scope module division $end
$var wire 32 ! a [31:0] $end
$var wire 32 " b [31:0] $end
$var wire 1 # clk $end
$var wire 1 $ divrst $end
$var wire 1 % signdiv $end
$var wire 32 & ur [31:0] $end
$var wire 32 ' uq [31:0] $end
$var wire 32 ( shiftedb [31:0] $end
$var reg 5 ) aligncnt [4:0] $end
$var reg 5 * constind [4:0] $end
$var reg 1 + nxt $end
$var reg 32 , q [31:0] $end
$var reg 32 - r [31:0] $end
$var reg 32 . ua [31:0] $end
$var reg 32 / ub [31:0] $end
$scope module aligner $end
$var wire 32 0 ala [31:0] $end
$var wire 32 1 alb [31:0] $end
$var wire 1 $ alrst $end
$var wire 1 # clk $end
$var reg 16 2 ahi [15:0] $end
$var reg 1 3 ahizero $end
$var reg 16 4 alo [15:0] $end
$var reg 17 5 bhi [16:0] $end
$var reg 17 6 blo [16:0] $end
$var reg 5 7 blo_cnt [4:0] $end
$var reg 1 8 end_lo $end
$var reg 5 9 i [4:0] $end
$var reg 32 : shiftb [31:0] $end
$var reg 32 ; shifted [31:0] $end
$upscope $end
$scope module divider $end
$var wire 1 # clk $end
$var wire 32 < divua [31:0] $end
$var wire 32 = divub [31:0] $end
$var wire 1 + divurst $end
$var wire 32 > realb [31:0] $end
$var reg 32 ? divuq [31:0] $end
$var reg 32 @ divur [31:0] $end
$var reg 32 A quotient [31:0] $end
$var reg 32 B rega [31:0] $end
$var reg 32 C regb [31:0] $end
$upscope $end
$upscope $end
$upscope $end
$enddefinitions $end
#30
$dumpvars
b0xxxxxxxxxxxxxxxxxxxxxxxxxxxxxx C
bx B
bx00 A
bx @
bx00 ?
b1 >
bx =
b11111111111111111111111111111111 <
bx ;
bx :
b0 9
08
b0 7
b1 6
b0 5
b1111111111111111 4
03
b1111111111111111 2
b1 1
b11111111111111111111111111111111 0
b1 /
b11111111111111111111111111111111 .
bx -
bx00 ,
0+
b11111 *
b10 )
bx (
bx00 '
bx &
0%
0$
1#
b1 "
b11111111111111111111111111111111 !
$end
#40
0#
#50
bx000 ,
bx000 '
bx000 ?
b1 7
b10 6
b1 9
b0xxxxxxxxxxxxxxxxxxxxxxxxxxxxx C
bx000 A
b11 )
1#
#60
0#
#70
bx0000 ,
bx0000 '
bx0000 ?
b100 )
b0xxxxxxxxxxxxxxxxxxxxxxxxxxxx C
bx0000 A
b10 7
b100 6
b10 9
1#
#80
0#
#90
bx00000 ,
bx00000 '
bx00000 ?
b11 7
b1000 6
b11 9
b0xxxxxxxxxxxxxxxxxxxxxxxxxxx C
bx00000 A
b101 )
1#
#100
0#
#110
bx000000 ,
bx000000 '
bx000000 ?
b110 )
b0xxxxxxxxxxxxxxxxxxxxxxxxxx C
bx000000 A
b100 7
b10000 6
b100 9
1#
#120
0#
#130
bx0000000 ,
bx0000000 '
bx0000000 ?
b101 7
b100000 6
b101 9
b0xxxxxxxxxxxxxxxxxxxxxxxxx C
bx0000000 A
b111 )
1#
#140
0#
#150
bx00000000 ,
bx00000000 '
bx00000000 ?
b1000 )
b0xxxxxxxxxxxxxxxxxxxxxxxx C
bx00000000 A
b110 7
b1000000 6
b110 9
1#
#160
0#
#170
bx000000000 ,
bx000000000 '
bx000000000 ?
b111 7
b10000000 6
b111 9
b0xxxxxxxxxxxxxxxxxxxxxxx C
bx000000000 A
b1001 )
1#
#180
0#
#190
bx0000000000 ,
bx0000000000 '
bx0000000000 ?
b1010 )
b0xxxxxxxxxxxxxxxxxxxxxx C
bx0000000000 A
b1000 7
b100000000 6
b1000 9
1#
#200
0#
#210
bx00000000000 ,
bx00000000000 '
bx00000000000 ?
b1001 7
b1000000000 6
b1001 9
b0xxxxxxxxxxxxxxxxxxxxx C
bx00000000000 A
b1011 )
1#
#220
0#
#230
bx000000000000 ,
bx000000000000 '
bx000000000000 ?
b1100 )
b0xxxxxxxxxxxxxxxxxxxx C
bx000000000000 A
b1010 7
b10000000000 6
b1010 9
1#
#240
0#
#250
bx0000000000000 ,
bx0000000000000 '
bx0000000000000 ?
b1011 7
b100000000000 6
b1011 9
b0xxxxxxxxxxxxxxxxxxx C
bx0000000000000 A
b1101 )
1#
#260
0#
#270
bx00000000000000 ,
bx00000000000000 '
bx00000000000000 ?
b1110 )
b0xxxxxxxxxxxxxxxxxx C
bx00000000000000 A
b1100 7
b1000000000000 6
b1100 9
1#
#280
0#
#290
bx000000000000000 ,
bx000000000000000 '
bx000000000000000 ?
b1101 7
b10000000000000 6
b1101 9
b0xxxxxxxxxxxxxxxxx C
bx000000000000000 A
b1111 )
1#
#300
0#
#310
bx0000000000000000 ,
bx0000000000000000 '
bx0000000000000000 ?
b10000 )
b0xxxxxxxxxxxxxxxx C
bx0000000000000000 A
b1110 7
b100000000000000 6
b1110 9
1#
#320
0#
#330
bx00000000000000000 ,
bx00000000000000000 '
bx00000000000000000 ?
b1111 7
b1000000000000000 6
b1111 9
b0xxxxxxxxxxxxxxx C
bx00000000000000000 A
b10001 )
1#
#340
0#
#350
bx000000000000000000 ,
bx000000000000000000 '
bx000000000000000000 ?
b10010 )
b0xxxxxxxxxxxxxx C
bx000000000000000000 A
b10000 7
b10000000000000000 6
b10000 9
1#
#360
0#
#370
bx0000000000000000000 ,
b10000000000000000000000000000000 (
b10000000000000000000000000000000 :
b10000000000000000000000000000000 =
bx0000000000000000000 '
bx0000000000000000000 ?
18
b10000000000000000000000000000000 ;
b0xxxxxxxxxxxxx C
bx0000000000000000000 A
1+
b10011 )
1#
#380
0#
#390
b11111111111111111111111111111111 -
b0 ,
b11111111111111111111111111111111 &
b11111111111111111111111111111111 @
b0 '
b0 ?
0+
b10000000000000000000000000000000 C
b11111111111111111111111111111111 B
b0 A
1#
#400
0#
#410
b1111111111111111111111111111111 -
b1 ,
b1111111111111111111111111111111 &
b1111111111111111111111111111111 @
b1 '
b1 ?
b1000000000000000000000000000000 C
b1 A
b1111111111111111111111111111111 B
1#
#420
0#
#430
b111111111111111111111111111111 -
b11 ,
b111111111111111111111111111111 &
b111111111111111111111111111111 @
b11 '
b11 ?
b100000000000000000000000000000 C
b11 A
b111111111111111111111111111111 B
1#
#440
0#
#450
b11111111111111111111111111111 -
b111 ,
b11111111111111111111111111111 &
b11111111111111111111111111111 @
b111 '
b111 ?
b10000000000000000000000000000 C
b111 A
b11111111111111111111111111111 B
1#
#460
0#
#470
b1111111111111111111111111111 -
b1111 ,
b1111111111111111111111111111 &
b1111111111111111111111111111 @
b1111 '
b1111 ?
b1000000000000000000000000000 C
b1111 A
b1111111111111111111111111111 B
1#
#480
0#
#490
b111111111111111111111111111 -
b11111 ,
b111111111111111111111111111 &
b111111111111111111111111111 @
b11111 '
b11111 ?
b100000000000000000000000000 C
b11111 A
b111111111111111111111111111 B
1#
#500
0#
#510
b11111111111111111111111111 -
b111111 ,
b11111111111111111111111111 &
b11111111111111111111111111 @
b111111 '
b111111 ?
b10000000000000000000000000 C
b111111 A
b11111111111111111111111111 B
1#
#520
0#
#530
b1111111111111111111111111 -
b1111111 ,
b1111111111111111111111111 &
b1111111111111111111111111 @
b1111111 '
b1111111 ?
b1000000000000000000000000 C
b1111111 A
b1111111111111111111111111 B
1#
#540
0#
#550
b111111111111111111111111 -
b11111111 ,
b111111111111111111111111 &
b111111111111111111111111 @
b11111111 '
b11111111 ?
b100000000000000000000000 C
b11111111 A
b111111111111111111111111 B
1#
#560
0#
#570
b11111111111111111111111 -
b111111111 ,
b11111111111111111111111 &
b11111111111111111111111 @
b111111111 '
b111111111 ?
b10000000000000000000000 C
b111111111 A
b11111111111111111111111 B
1#
#580
0#
#590
b1111111111111111111111 -
b1111111111 ,
b1111111111111111111111 &
b1111111111111111111111 @
b1111111111 '
b1111111111 ?
b1000000000000000000000 C
b1111111111 A
b1111111111111111111111 B
1#
#600
0#
#610
b111111111111111111111 -
b11111111111 ,
b111111111111111111111 &
b111111111111111111111 @
b11111111111 '
b11111111111 ?
b100000000000000000000 C
b11111111111 A
b111111111111111111111 B
1#
#620
0#
#630
b11111111111111111111 -
b111111111111 ,
b11111111111111111111 &
b11111111111111111111 @
b111111111111 '
b111111111111 ?
b10000000000000000000 C
b111111111111 A
b11111111111111111111 B
1#
#640
0#
#650
b1111111111111111111 -
b1111111111111 ,
b1111111111111111111 &
b1111111111111111111 @
b1111111111111 '
b1111111111111 ?
b1000000000000000000 C
b1111111111111 A
b1111111111111111111 B
1#
#660
0#
#670
b111111111111111111 -
b11111111111111 ,
b111111111111111111 &
b111111111111111111 @
b11111111111111 '
b11111111111111 ?
b100000000000000000 C
b11111111111111 A
b111111111111111111 B
1#
#680
0#
#690
b11111111111111111 -
b111111111111111 ,
b11111111111111111 &
b11111111111111111 @
b111111111111111 '
b111111111111111 ?
b10000000000000000 C
b111111111111111 A
b11111111111111111 B
1#
#700
0#
#710
b1111111111111111 -
b1111111111111111 ,
b1111111111111111 &
b1111111111111111 @
b1111111111111111 '
b1111111111111111 ?
b1000000000000000 C
b1111111111111111 A
b1111111111111111 B
1#
#720
0#
#730
b111111111111111 -
b11111111111111111 ,
b111111111111111 &
b111111111111111 @
b11111111111111111 '
b11111111111111111 ?
b100000000000000 C
b11111111111111111 A
b111111111111111 B
1#
#740
0#
#750
b11111111111111 -
b111111111111111111 ,
b11111111111111 &
b11111111111111 @
b111111111111111111 '
b111111111111111111 ?
b10000000000000 C
b111111111111111111 A
b11111111111111 B
1#
#760
0#
#770
b1111111111111 -
b1111111111111111111 ,
b1111111111111 &
b1111111111111 @
b1111111111111111111 '
b1111111111111111111 ?
b1000000000000 C
b1111111111111111111 A
b1111111111111 B
1#
#780
0#
#790
b111111111111 -
b11111111111111111111 ,
b111111111111 &
b111111111111 @
b11111111111111111111 '
b11111111111111111111 ?
b100000000000 C
b11111111111111111111 A
b111111111111 B
1#
#800
0#
#810
b11111111111 -
b111111111111111111111 ,
b11111111111 &
b11111111111 @
b111111111111111111111 '
b111111111111111111111 ?
b10000000000 C
b111111111111111111111 A
b11111111111 B
1#
#820
0#
#830
b1111111111 -
b1111111111111111111111 ,
b1111111111 &
b1111111111 @
b1111111111111111111111 '
b1111111111111111111111 ?
b1000000000 C
b1111111111111111111111 A
b1111111111 B
1#
#840
0#
#850
b111111111 -
b11111111111111111111111 ,
b111111111 &
b111111111 @
b11111111111111111111111 '
b11111111111111111111111 ?
b100000000 C
b11111111111111111111111 A
b111111111 B
1#
#860
0#
#870
b11111111 -
b111111111111111111111111 ,
b11111111 &
b11111111 @
b111111111111111111111111 '
b111111111111111111111111 ?
b10000000 C
b111111111111111111111111 A
b11111111 B
1#
#880
0#
#890
b1111111 -
b1111111111111111111111111 ,
b1111111 &
b1111111 @
b1111111111111111111111111 '
b1111111111111111111111111 ?
b1000000 C
b1111111111111111111111111 A
b1111111 B
1#
#900
0#
#910
b111111 -
b11111111111111111111111111 ,
b111111 &
b111111 @
b11111111111111111111111111 '
b11111111111111111111111111 ?
b100000 C
b11111111111111111111111111 A
b111111 B
1#
#920
0#
#930
b11111 -
b111111111111111111111111111 ,
b11111 &
b11111 @
b111111111111111111111111111 '
b111111111111111111111111111 ?
b10000 C
b111111111111111111111111111 A
b11111 B
1#
#940
0#
#950
b1111 -
b1111111111111111111111111111 ,
b1111 &
b1111 @
b1111111111111111111111111111 '
b1111111111111111111111111111 ?
b1000 C
b1111111111111111111111111111 A
b1111 B
1#
#960
0#
#970
b111 -
b11111111111111111111111111111 ,
b111 &
b111 @
b11111111111111111111111111111 '
b11111111111111111111111111111 ?
b100 C
b11111111111111111111111111111 A
b111 B
1#
#980
0#
#990
b11 -
b111111111111111111111111111111 ,
b11 &
b11 @
b111111111111111111111111111111 '
b111111111111111111111111111111 ?
b10 C
b111111111111111111111111111111 A
b11 B
1#
#1000
0#
#1010
b1 -
b1111111111111111111111111111111 ,
b1 &
b1 @
b1111111111111111111111111111111 '
b1111111111111111111111111111111 ?
b1 C
b1111111111111111111111111111111 A
b1 B
1#
#1020
0#
#1030
b0 -
b11111111111111111111111111111111 ,
b0 &
b0 @
b11111111111111111111111111111111 '
b11111111111111111111111111111111 ?
b0 C
b11111111111111111111111111111111 A
b0 B
1#
